mokola/__init__.py
mokola/stocks/Gse.py
mokola/stocks/Stocks.py
mokola/stocks/__init__.py
mokola-1.2.5.dist-info/METADATA
mokola-1.2.5.dist-info/WHEEL
mokola-1.2.5.dist-info/top_level.txt
mokola-1.2.5.dist-info/RECORD
